alphaVantageAPI/__init__.py
alphaVantageAPI/_base_pandas_object.py
alphaVantageAPI/_extension.py
alphaVantageAPI/alphavantage.py
alphaVantageAPI/utils.py
alphaVantageAPI/validate_parameters.py
alphaVantageAPI/__pycache__/__init__.cpython-37.pyc
alphaVantageAPI/__pycache__/_base_pandas_object.cpython-37.pyc
alphaVantageAPI/__pycache__/_extension.cpython-37.pyc
alphaVantageAPI/__pycache__/alphavantage.cpython-37.pyc
alphaVantageAPI/__pycache__/utils.cpython-37.pyc
alphaVantageAPI/__pycache__/validate_parameters.cpython-37.pyc
alphaVantageAPI/data/api.json
alphaVantage_api-1.0.18.dist-info/LICENSE.txt
alphaVantage_api-1.0.18.dist-info/METADATA
alphaVantage_api-1.0.18.dist-info/WHEEL
alphaVantage_api-1.0.18.dist-info/top_level.txt
alphaVantage_api-1.0.18.dist-info/RECORD
