Metadata-Version: 2.1
Name: alphaVantage-api
Version: 1.0.18
Summary: An Opinionated AlphaVantage API Wrapper in Python 3.7
Home-page: https://github.com/twopirllc/AlphaVantageAPI
Author: Kevin Johnson
Author-email: appliedmathkj@gmail.com
License: MIT
Keywords: AlphaVantage,API,Equities,FOREX,Digital/Crypto,TA,Technicals,Sectors
Platform: UNKNOWN
Classifier: Programming Language :: Python :: 3.7
Classifier: Development Status :: 5 - Production/Stable
Classifier: License :: OSI Approved :: MIT License
Classifier: Intended Audience :: Developers
Classifier: Intended Audience :: Financial and Insurance Industry
Classifier: Topic :: Office/Business :: Financial :: Investment
Classifier: Topic :: Utilities
Requires-Dist: requests
Requires-Dist: pandas
Provides-Extra: openpyxl
Requires-Dist: openpyxl ; extra == 'openpyxl'
